{
  "index": 328,
  "cot_content": "We need to find number of bits in binary representation of decimal? Actually \"base-16 number 66666\" means hex digits? In hex, 6 6 6 6 6 = hex number 0x66666. Convert to decimal? 0x66666 = 6*16^4 +6*16^3+6*16^2+6*16+6. Compute: 16^2=256, 16^3=4096, 16^4=65536. So value=6*65536+6*4096+6*256+6*16+6=393216+24576+1536+96+6=393216+24576=417792; +1536=419328; +96=419424; +6=419430. So decimal 419430. Binary length? Find highest power of 2 <=419430. 2^19=524288 too large. 2^18=262144. 2^19? Actually 2^18=262144, 2^19=524288. So between. So need 19 bits? If number >=2^18, then need 19 bits? Actually bits needed = floor(log2(n))+1. log2(419430)=? 2^18=262144; 2^19=524288. So log2 is between 18 and 19. So floor=18. So need 19 bits. So answer 19.",
  "response_content": "19",
  "sentences": [
    "We need to find number of bits in binary representation of decimal?",
    "Actually \"base-16 number 66666\" means hex digits?",
    "In hex, 6 6 6 6 6 = hex number 0x66666. Convert to decimal?",
    "0x66666 = 6*16^4 +6*16^3+6*16^2+6*16+6.",
    "Compute: 16^2=256, 16^3=4096, 16^4=65536.",
    "So value=6*65536+6*4096+6*256+6*16+6=393216+24576+1536+96+6=393216+24576=417792; +1536=419328; +96=419424; +6=419430. So decimal 419430. Binary length?",
    "Find highest power of 2 <=419430. 2^19=524288 too large. 2^18=262144. 2^19? Actually 2^18=262144, 2^19=524288. So between.",
    "So need 19 bits?",
    "If number >=2^18, then need 19 bits?",
    "Actually bits needed = floor(log2(n))+1. log2(419430)=? 2^18=262144; 2^19=524288.",
    "So log2 is between 18 and 19. So floor=18.",
    "So need 19 bits. So answer 19."
  ],
  "seed": 328
}